LICENSE
README.md
setup.cfg
setup.py
.github/workflows/ci.yaml
rtipc/__init__.py
rtipc/rtipc.py
rtipc/version.py
rtipc.egg-info/PKG-INFO
rtipc.egg-info/SOURCES.txt
rtipc.egg-info/dependency_links.txt
rtipc.egg-info/requires.txt
rtipc.egg-info/top_level.txt
test/test_once.py