Metadata-Version: 2.4
Name: rtipc
Version: 0.0.0.2
Summary: A Python binding for https://gitlab.com/etherlab.org/rtipc
Home-page: https://github.com/cielavenir/rtipc
Author: cielavenir
Author-email: cielartisan@gmail.com
License: LGPL-3.0-or-later or MIT
Classifier: Development Status :: 4 - Beta
Classifier: Intended Audience :: Developers
Classifier: Operating System :: POSIX
Classifier: Topic :: Software Development :: Libraries
Classifier: Topic :: Utilities
Classifier: Programming Language :: Python :: 2
Classifier: Programming Language :: Python :: 2.7
Classifier: Programming Language :: Python :: 3
Classifier: Programming Language :: Python :: 3.4
Classifier: Programming Language :: Python :: 3.5
Classifier: Programming Language :: Python :: 3.6
Classifier: Programming Language :: Python :: Implementation :: PyPy
License-File: LICENSE
Requires-Dist: six
Requires-Dist: aenum~=2.2; python_version < "3"
Dynamic: license-file
